README.rst
setup.cfg
setup.py
arv/__init__.py
arv.autotest.egg-info/PKG-INFO
arv.autotest.egg-info/SOURCES.txt
arv.autotest.egg-info/dependency_links.txt
arv.autotest.egg-info/entry_points.txt
arv.autotest.egg-info/namespace_packages.txt
arv.autotest.egg-info/not-zip-safe
arv.autotest.egg-info/requires.txt
arv.autotest.egg-info/top_level.txt
arv/autotest/__init__.py
arv/autotest/cmdline.py
arv/autotest/config.py
arv/autotest/event_filters.py
arv/autotest/main.py
arv/autotest/reporters.py
arv/autotest/runner.py
arv/autotest/utils.py
arv/autotest/validators.py
arv/autotest/images/failed.png
arv/autotest/images/succeed.png