Metadata-Version: 1.1
Name: arv.autotest
Version: 0.2.4
Summary: Run tests whenever a file changes
Home-page: https://github.com/patxoca/arv.autotest
Author: Alexis Roda
Author-email: alexis.roda.villalonga@gmail.com
License: GPLv3+
Platform: UNKNOWN
Classifier: Development Status :: 2 - Pre-Alpha
Classifier: Environment :: Console
Classifier: Intended Audience :: Developers
Classifier: License :: OSI Approved :: GNU General Public License v3 or later (GPLv3+)
Classifier: Natural Language :: English
Classifier: Programming Language :: Python :: 2.6
Classifier: Programming Language :: Python :: 2.7
Classifier: Programming Language :: Python :: 3.3
Classifier: Programming Language :: Python :: 3.4
Classifier: Topic :: Software Development :: Testing
